datasetdl/__init__.py
datasetdl/download.py
datasetdl/datasets/revenue.csv
datasetdl-0.1.1.dist-info/METADATA
datasetdl-0.1.1.dist-info/WHEEL
datasetdl-0.1.1.dist-info/top_level.txt
datasetdl-0.1.1.dist-info/RECORD
